{
  "generated_at": "2026-04-30T04:36:24.308Z",
  "surface": "approved",
  "slug": "/compare/horse-lease-vs-horse-purchase/",
  "patch_key": "compare__horse-lease-vs-horse-purchase",
  "output_url": "/compare/horse-lease-vs-horse-purchase/",
  "filePath": "dist/compare/horse-lease-vs-horse-purchase/index.html",
  "query_family": "comparison",
  "answer_shape": "top_comparison_table",
  "page_type": "comparison",
  "cluster": "horse-lease-and-trial",
  "editable_zones": [
    {
      "name": "quick_answer_block",
      "description": "Top-of-page short answer summary."
    },
    {
      "name": "top_answer_module",
      "description": "Primary answer-shape module rendered directly under quick answer."
    },
    {
      "name": "faq_block",
      "description": "FAQ / question-and-answer editable content block."
    },
    {
      "name": "related_links_block",
      "description": "Related links / adjacent page recommendations."
    },
    {
      "name": "routing_block",
      "description": "Handoff and CTA copy block."
    }
  ],
  "locked_invariants": {
    "keys": [
      "route",
      "canonical_url",
      "schema_type",
      "entity_ids",
      "sitemap_inclusion_key",
      "authority_graph_membership"
    ],
    "route": "/compare/horse-lease-vs-horse-purchase/",
    "canonical_url": "https://horselegalguide.com/compare/horse-lease-vs-horse-purchase/",
    "schema_type": "Article",
    "sitemap_inclusion_key": "/compare/horse-lease-vs-horse-purchase/",
    "entity_ids": []
  },
  "validation_scope": "page_local",
  "manifest_version": 1
}
